{
  "structureMenu": {
    "classes": {
      "Прочее": ""
    }
  },
  "classes": {
    "FTPСоединение": {
      "name": "FTPСоединение",
      "name_en": "FtpConnection",
      "description": "Предназначен для работы с файлами посредством FTP.",
      "properties": {
        "ЗащищенноеСоединение": {
          "name": "ЗащищенноеСоединение",
          "name_en": "SecureConnection",
          "description": "Защищённое соединение.",
          "value": "Содержит объект защищённого соединения.",
          "access": "Чтение"
        },
        "Пароль": {
          "name": "Пароль",
          "name_en": "Password",
          "description": "Пароль.",
          "value": "Пароль.",
          "access": "Чтение"
        },
        "ПассивныйРежим": {
          "name": "ПассивныйРежим",
          "name_en": "PassiveMode",
          "description": "Пассивный режим.",
          "value": "Пассивный режим.",
          "access": "Чтение"
        },
        "Пользователь": {
          "name": "Пользователь",
          "name_en": "User",
          "description": "Имя пользователя.",
          "value": "Имя пользователя.",
          "access": "Чтение"
        },
        "Порт": {
          "name": "Порт",
          "name_en": "Port",
          "description": "Порт.",
          "value": "Порт.",
          "access": "Чтение"
        },
        "Прокси": {
          "name": "Прокси",
          "name_en": "Proxy",
          "description": "Прокси.",
          "value": "Прокси.",
          "access": "Чтение"
        },
        "Сервер": {
          "name": "Сервер",
          "name_en": "Server",
          "description": "Сервер.",
          "value": "Сервер, с которым устанавливается соединение.",
          "access": "Чтение"
        },
        "Таймаут": {
          "name": "Таймаут",
          "name_en": "Timeout",
          "description": "Таймаут.",
          "value": "Таймаут в секундах. 0 - без таймаута.",
          "access": "Чтение"
        }
      },
      "constructors": {
        "По умолчанию": {
          "name": "По умолчанию",
          "signature": "(server: Произвольный, port?: Произвольный, userName?: Произвольный, password?: Произвольный, proxy?: ИнтернетПрокси, passiveConnection?: Произвольный, timeout?: Произвольный, secureConnection?: Произвольный)",
          "description": "Создаёт объект FTPСоединение.",
          "returns": "FTPСоединение.",
          "params": {
            "server": "Подключаемый сервер.",
            "port": "Порт. Необязательный",
            "userName": "Имя пользователя. Необязательный",
            "password": "Пароль. Необязательный",
            "proxy": "Прокси. Необязательный",
            "passiveConnection": "Пассивный режим. Необязательный",
            "timeout": "Таймаут. Необязательный",
            "secureConnection": "Защищённое соединение. Необязательный"
          }
        }
      },
      "methods": {
        "НайтиФайлы": {
          "name": "НайтиФайлы",
          "name_en": "FindFiles",
          "description": "Ищет файлы на удалённом сервере.",
          "returns": "Массив.",
          "signature": {
            "default": {
              "СтрокаПараметров": "(path: Строка, mask?: Строка, recursive?: Булево): Массив",
              "Параметры": {
                "path": "Путь.",
                "mask": "Маска. Необязательный",
                "recursive": "Искать во вложенных каталогах."
              }
            }
          }
        },
        "Записать": {
          "name": "Записать",
          "name_en": "Put",
          "description": "Записывает локальный файл на удалённый сервер.",
          "signature": {
            "default": {
              "СтрокаПараметров": "(localFilePath: Строка, remoteFilePath: Строка)",
              "Параметры": {
                "localFilePath": "Путь к файлу на локальном компьютере.",
                "remoteFilePath": "Путь к файлу на удалённом сервере."
              }
            }
          }
        },
        "Получить": {
          "name": "Получить",
          "name_en": "Get",
          "description": "Скачивает файл с удалённого сервера.",
          "signature": {
            "default": {
              "СтрокаПараметров": "(remoteFilePath: Строка, localFilePath: Строка)",
              "Параметры": {
                "remoteFilePath": "Путь к файлу ан удалённом сервере.",
                "localFilePath": "Путь к файлу, в который будет записан удалённый файл."
              }
            }
          }
        },
        "Удалить": {
          "name": "Удалить",
          "name_en": "Delete",
          "description": "Удаляет файлы на сервере.",
          "signature": {
            "default": {
              "СтрокаПараметров": "(path: Строка, mask?: Строка)",
              "Параметры": {
                "path": "Путь.",
                "mask": "Маска. Необязательный"
              }
            }
          }
        },
        "Переместить": {
          "name": "Переместить",
          "name_en": "Move",
          "description": "Перемещает файл на удалённом сервере.",
          "signature": {
            "default": {
              "СтрокаПараметров": "(currentPath: Строка, newPath: Строка)",
              "Параметры": {
                "currentPath": "Путь к перемещаемому файлу.",
                "newPath": "Новый Путь файла."
              }
            }
          }
        },
        "ТекущийКаталог": {
          "name": "ТекущийКаталог",
          "name_en": "GetCurrentDirectory",
          "description": "Возвращает текущий каталог соединения.",
          "returns": "Текущий каталог.",
          "signature": {
            "default": {
              "СтрокаПараметров": "(): Строка",
              "Параметры": {}
            }
          }
        },
        "УстановитьТекущийКаталог": {
          "name": "УстановитьТекущийКаталог",
          "name_en": "SetCurrentDirectory",
          "description": "Устанавливает текущий каталог соединения.",
          "signature": {
            "default": {
              "СтрокаПараметров": "(directory: Строка)",
              "Параметры": {
                "directory": "Каталог."
              }
            }
          }
        },
        "СоздатьКаталог": {
          "name": "СоздатьКаталог",
          "name_en": "CreateDirectory",
          "description": "Создаёт каталог на удалённом сервере.",
          "signature": {
            "default": {
              "СтрокаПараметров": "(dirName: Строка)",
              "Параметры": {
                "dirName": "Имя каталога."
              }
            }
          }
        }
      }
    },
    "FTPФайл": {
      "name": "FTPФайл",
      "name_en": "FtpFile",
      "description": "Описывает файл на удалённом сервере.",
      "properties": {
        "Имя": {
          "name": "Имя",
          "name_en": "Name",
          "description": "Имя файла.",
          "value": "Имя файла или каталога.",
          "access": "Чтение"
        },
        "ИмяБезРасширения": {
          "name": "ИмяБезРасширения",
          "name_en": "BaseName",
          "description": "Имя без расширения.",
          "value": "Имя файла или каталога без расширения.",
          "access": "Чтение"
        },
        "ПолноеИмя": {
          "name": "ПолноеИмя",
          "name_en": "FullName",
          "description": "Полное имя.",
          "value": "Полный путь к файлу.",
          "access": "Чтение"
        },
        "Путь": {
          "name": "Путь",
          "name_en": "Path",
          "description": "Путь.",
          "value": "Каталог, в котором находится файл.",
          "access": "Чтение"
        },
        "Расширение": {
          "name": "Расширение",
          "name_en": "Extension",
          "description": "Расширение.",
          "value": "Расширение файла.",
          "access": "Чтение"
        }
      },
      "methods": {
        "ЭтоФайл": {
          "name": "ЭтоФайл",
          "name_en": "IsFile",
          "description": "Определяет, что путь указывает на файл.",
          "returns": "true false , если это файл,- это каталог.",
          "signature": {
            "default": {
              "СтрокаПараметров": "(): Булево",
              "Параметры": {}
            }
          }
        },
        "ЭтоКаталог": {
          "name": "ЭтоКаталог",
          "name_en": "IsDirectory",
          "description": "Определяет, что путь указывает на каталог.",
          "returns": "true false , если это каталог,- это файл.",
          "signature": {
            "default": {
              "СтрокаПараметров": "(): Булево",
              "Параметры": {}
            }
          }
        },
        "ПолучитьВремяИзменения": {
          "name": "ПолучитьВремяИзменения",
          "name_en": "GetModificationTime",
          "description": "Получает время последнего изменения файла.",
          "returns": "Время последнего изменения.",
          "signature": {
            "default": {
              "СтрокаПараметров": "(): Дата",
              "Параметры": {}
            }
          }
        },
        "ПолучитьНевидимость": {
          "name": "ПолучитьНевидимость",
          "name_en": "GetHidden",
          "description": "Получает атрибут невидимости.",
          "returns": "true false , если у файла есть атрибут \"Скрыты\",в противном случае.",
          "signature": {
            "default": {
              "СтрокаПараметров": "(): Булево",
              "Параметры": {}
            }
          }
        },
        "ПолучитьТолькоЧтение": {
          "name": "ПолучитьТолькоЧтение",
          "name_en": "GetReadOnly",
          "description": "Получает атрибут \"Только для чтения\".",
          "returns": "true false , если установлен атрибут \"Только для чтения\",в противном случае.",
          "signature": {
            "default": {
              "СтрокаПараметров": "(): Булево",
              "Параметры": {}
            }
          }
        },
        "Размер": {
          "name": "Размер",
          "name_en": "Size",
          "description": "Определяет размер файла.",
          "returns": "Размер файла.",
          "signature": {
            "default": {
              "СтрокаПараметров": "(): Число",
              "Параметры": {}
            }
          }
        }
      }
    }
  },
  "systemEnum": {}
}